{"mealName":"General_Tsos_Chicken","mealIngredients":["Chicken Breast","Plain Flour","Egg","Starch","Baking Powder","Salt","Onion Salt","Garlic Powder","Water","Chicken Stock","Duck Sauce","Soy Sauce","Honey","Rice Vinegar","Sesame Seed Oil"],"mealMeasurements":["1 1/2 ","3/4 cup ","1","2 tbs","1 tbs","1 tsp ","1/2 tsp","1/4 tsp","3/4 cup ","1/2 cup ","1/4 cup","3 tbs","2 tbs","1 tbs","2 tbs"],"mealInstructions":"DIRECTIONS:\r\nSTEP 1 - SAUCE\r\nIn a bowl, add 2 Cups of water, 2 Tablespoon soy sauce, 2 Tablespoon white vinegar, sherry cooking wine, 1/4 Teaspoon white pepper, minced ginger, minced garlic, hot pepper, ketchup, hoisin sauce, and sugar.\r\nMix together well and set aside.\r\nSTEP 2 - MARINATING THE CHICKEN\r\nIn a bowl, add the chicken, 1 pinch of salt, 1 pinch of white pepper, 2 egg whites, and 3 Tablespoon of corn starch\r\nSTEP 3 - DEEP FRY THE CHICKEN\r\nDeep fry the chicken at 350 degrees for 3-4 minutes or until it is golden brown and loosen up the chicken so that they don\u0027t stick together.\r\nSet the chicken aside.\r\nSTEP 4 - STIR FRY\r\nAdd the sauce to the wok and then the broccoli and wait until it is boiling.\r\nTo thicken the sauce, whisk together 2 Tablespoon of cornstarch and 4 Tablespoon of water in a bowl and slowly add to your stir-fry until it\u0027s the right thickness.\r\nNext add in the chicken and stir-fry for a minute and serve on a plate","mealCategory":"Chicken","mealArea":"Chinese"}